mobiflows/__about__.py
mobiflows/__init__.py
mobiflows/algorithm.py
mobiflows/dtypes.py
mobiflows-1.0.0.dist-info/METADATA
mobiflows-1.0.0.dist-info/WHEEL
mobiflows-1.0.0.dist-info/licenses/LICENSE.txt
mobiflows-1.0.0.dist-info/RECORD
